[
  {
    "name": "Superior Draki Supply Box",
    "lvl": "+0",
    "buy_price": 19000000,
    "buy_strategy": "Spread Filtreli",
    "count": 1,
    "sell_strategy": "Auto/Min",
    "sell_price": 21334660,
    "server": "",
    "buy_fixed": true,
    "sell_fixed": false
  },
  {
    "name": "Old Draki Supply Box",
    "lvl": "+0",
    "buy_price": 10340000,
    "buy_strategy": "Spread Filtreli",
    "count": 1,
    "sell_strategy": "Auto/Q1",
    "sell_price": 11000000,
    "server": "",
    "buy_fixed": true,
    "sell_fixed": false
  },
  {
    "name": "Fortified Sterling Silver Gemstone",
    "lvl": "+0",
    "buy_price": 9020000,
    "buy_strategy": "Spread Filtreli",
    "count": 1,
    "sell_strategy": "Auto/Q1",
    "sell_price": 9734999,
    "server": "",
    "buy_fixed": true,
    "sell_fixed": false
  },
  {
    "name": "silvery gem",
    "lvl": "+0",
    "buy_price": 9015000,
    "buy_strategy": "Spread Filtreli",
    "count": 1,
    "sell_strategy": "Auto/Q1",
    "sell_price": 9691888,
    "server": "",
    "buy_fixed": true,
    "sell_fixed": false
  },
  {
    "name": "blue gem",
    "lvl": "+0",
    "buy_price": 4035000,
    "buy_strategy": "Spread Filtreli",
    "count": 1,
    "sell_strategy": "Auto/Q1",
    "sell_price": 4474999,
    "server": "",
    "buy_fixed": true,
    "sell_fixed": false
  },
  {
    "name": "green gem",
    "lvl": "+0",
    "buy_price": 2000000,
    "buy_strategy": "Spread Filtreli",
    "count": 1,
    "sell_strategy": "Auto/Min",
    "sell_price": 2334000,
    "server": "",
    "buy_fixed": true,
    "sell_fixed": false
  },
  {
    "name": "black gem",
    "lvl": "+0",
    "buy_price": 2000000,
    "buy_strategy": "Spread Filtreli",
    "count": 1,
    "sell_strategy": "Auto/Q1",
    "sell_price": 2269999,
    "server": "",
    "buy_fixed": true,
    "sell_fixed": false
  },
  {
    "name": "Blue Treasure Chest",
    "lvl": "+0",
    "buy_price": 8240000,
    "buy_strategy": "Spread Filtreli",
    "count": 1,
    "sell_strategy": "Auto/Min",
    "sell_price": 8999777,
    "server": "",
    "buy_fixed": true,
    "sell_fixed": false
  },
  {
    "name": "Green Treasure Chest",
    "lvl": "+0",
    "buy_price": 3520000,
    "buy_strategy": "Min",
    "count": 1,
    "sell_strategy": "Auto/Mod",
    "sell_price": 4019999,
    "server": "",
    "buy_fixed": true,
    "sell_fixed": false
  },
  {
    "name": "Red Treasure Chest",
    "lvl": "+0",
    "buy_price": 2500000,
    "buy_strategy": "Min",
    "count": 1,
    "sell_strategy": "Auto/Min",
    "sell_price": 3350000,
    "server": "",
    "buy_fixed": true,
    "sell_fixed": false
  },
  {
    "name": "Fragment of Arrogance",
    "lvl": "+0",
    "buy_price": 2044444,
    "buy_strategy": "Spread Filtreli",
    "count": 1,
    "sell_strategy": "Auto/Min",
    "sell_price": 2749898,
    "server": "",
    "buy_fixed": true,
    "sell_fixed": false
  },
  {
    "name": "Fragment of Gluttony",
    "lvl": "+0",
    "buy_price": 2044444,
    "buy_strategy": "Spread Filtreli",
    "count": 1,
    "sell_strategy": "Auto/Min",
    "sell_price": 2794999,
    "server": "",
    "buy_fixed": true,
    "sell_fixed": false
  },
  {
    "name": "Fragment of Rage",
    "lvl": "+0",
    "buy_price": 8000000,
    "buy_strategy": "Spread Filtreli",
    "count": 1,
    "sell_strategy": "Auto/Q1",
    "sell_price": 9800000,
    "server": "",
    "buy_fixed": true,
    "sell_fixed": false
  },
  {
    "name": "Fragment of Lechery",
    "lvl": "+0",
    "buy_price": 20000000,
    "buy_strategy": "Spread Filtreli",
    "count": 1,
    "sell_strategy": "Auto/Min",
    "sell_price": 28977777,
    "server": "",
    "buy_fixed": true,
    "sell_fixed": false
  },
  {
    "name": "Fragment of Jealousy",
    "lvl": "+0",
    "buy_price": 30000000,
    "buy_strategy": "Spread Filtreli",
    "count": 1,
    "sell_strategy": "Auto/Min",
    "sell_price": 39800000,
    "server": "",
    "buy_fixed": true,
    "sell_fixed": false
  },
  {
    "name": "Fragment of Avarice",
    "lvl": "+0",
    "buy_price": 40000000,
    "buy_strategy": "Spread Filtreli",
    "count": 1,
    "sell_strategy": "Auto/Min",
    "sell_price": 49994999,
    "server": "",
    "buy_fixed": true,
    "sell_fixed": false
  },
  {
    "name": "Trinas Piece",
    "lvl": "+0",
    "buy_price": 84600000,
    "buy_strategy": "Spread Filtreli",
    "count": 1,
    "sell_strategy": "Auto/Min",
    "sell_price": 93184999,
    "server": "",
    "buy_fixed": true,
    "sell_fixed": false
  },
  {
    "name": "Weapon Breaker",
    "lvl": "+1",
    "buy_price": 5005013,
    "buy_strategy": "Spread Filtreli",
    "count": 1,
    "sell_strategy": "Auto/Min",
    "sell_price": 6299949,
    "server": "",
    "buy_fixed": true,
    "sell_fixed": false
  },
  {
    "name": "Spell Stone Powder",
    "lvl": "+0",
    "buy_price": 1383750,
    "buy_strategy": "Spread Filtreli",
    "count": 1,
    "sell_strategy": "Auto/Min",
    "sell_price": 1700000,
    "server": "",
    "buy_fixed": true,
    "sell_fixed": false
  },
  {
    "name": "Talisman Upgrade Item",
    "lvl": "+0",
    "buy_price": 1525000,
    "buy_strategy": "Spread Filtreli",
    "count": 1,
    "sell_strategy": "Auto/Min",
    "sell_price": 2099999,
    "server": "",
    "buy_fixed": true,
    "sell_fixed": false
  },
  {
    "name": "Blessed Upgrade Scroll",
    "lvl": "+0",
    "buy_price": 2280000,
    "buy_strategy": "Spread Filtreli",
    "count": 1,
    "sell_strategy": "Auto/Min",
    "sell_price": 2462500,
    "server": "",
    "buy_fixed": true,
    "sell_fixed": false
  }
]